itry/__init__.py
itry/_modidx.py
itry/atyp.py
itry/cons.py
itry/core.py
itry/iatt.py
itry/imod.py
itry/impr.py
itry/trys.py
itry/util.py
itry-0.0.18.dist-info/LICENSE
itry-0.0.18.dist-info/METADATA
itry-0.0.18.dist-info/WHEEL
itry-0.0.18.dist-info/entry_points.txt
itry-0.0.18.dist-info/top_level.txt
itry-0.0.18.dist-info/RECORD
