Metadata-Version: 2.1
Name: itry
Version: 0.0.18
Summary: itry
Home-page: https://github.com/dsm-72/itry
Author: dsm-72
Author-email: sumner.magruder@yale.edu
License: Apache Software License 2.0
Keywords: itry imod module import try except importlib trys types
Classifier: Development Status :: 4 - Beta
Classifier: Intended Audience :: Developers
Classifier: Natural Language :: English
Classifier: Programming Language :: Python :: 3.11
Classifier: License :: OSI Approved :: Apache Software License
Requires-Python: >=3.11
Provides-Extra: dev
License-File: LICENSE
